yst/__init__.py
yst/fp.py
yst/sh.py
yst/hack/__init__.py
yst/hack/forbiddenfruit.py
yst/hack/normal.py
yst-0.1.3.dist-info/METADATA
yst-0.1.3.dist-info/WHEEL
yst-0.1.3.dist-info/licenses/LICENSE
yst-0.1.3.dist-info/RECORD
